mueb_register/MRegister.py
mueb_register/__init__.py
mueb_register-0.0.1.dist-info/METADATA
mueb_register-0.0.1.dist-info/WHEEL
mueb_register-0.0.1.dist-info/entry_points.txt
mueb_register-0.0.1.dist-info/top_level.txt
mueb_register-0.0.1.dist-info/RECORD
